baghajotin007/__init__.py
baghajotin007/module.py
tests/__init__.py
tests/test_module.py
baghajotin007-0.1.0.dist-info/LICENSE.md
baghajotin007-0.1.0.dist-info/METADATA
baghajotin007-0.1.0.dist-info/WHEEL
baghajotin007-0.1.0.dist-info/top_level.txt
baghajotin007-0.1.0.dist-info/RECORD
