Metadata-Version: 2.1
Name: baghajotin007
Version: 0.1.0
Summary: A simple Python package for basic arithmetic operations
Home-page: https://github.com/Swaran66/EcoSalinity
Author: Swaranjit
Author-email: dextersaran@gmail.com
Classifier: Programming Language :: Python :: 3
Classifier: License :: OSI Approved :: MIT License
Classifier: Operating System :: OS Independent
Requires-Python: >=3.6
License-File: LICENSE.md
